README.md
hook_plug/__init__.py
hook_plug/hook_plug.py
hook_plug-0.1.0.dist-info/WHEEL
hook_plug-0.1.0.dist-info/METADATA
hook_plug-0.1.0.dist-info/RECORD
